petitparser/__init__.py
petitparser/character.py
petitparser/context.py
petitparser/string.py
petitparser/utils.py
petitparser/parser/__init__.py
petitparser/parser/actions.py
petitparser/parser/combinators.py
petitparser/parser/primitive.py
petitparser/parser/repeating.py
petitparser/statics/__init__.py
petitparser/tools/__init__.py
petitparser/tools/expression_builder.py
petitparser/tools/grammar_definition.py
petitparser-0.1.2.dist-info/LICENSE
petitparser-0.1.2.dist-info/METADATA
petitparser-0.1.2.dist-info/WHEEL
petitparser-0.1.2.dist-info/top_level.txt
petitparser-0.1.2.dist-info/RECORD
