Metadata-Version: 2.1
Name: petitparser
Version: 0.1.2
Summary: PetitParser implemented in Python
Home-page: https://github.com/profMagija/py-petitparser
Author: Nikola Bebić
Author-email: nikola.bebic99@gmail.com
License: MIT
Platform: UNKNOWN
Classifier: Development Status :: 4 - Beta
Classifier: Intended Audience :: Science/Research
Classifier: License :: OSI Approved :: MIT License
Classifier: Programming Language :: Python :: 3.8
License-File: LICENSE
